setup.py
test/__init__.py
test/test_active_query_builder_api.py
test/test_condition.py
test/test_condition_group.py
test/test_hidden_column.py
test/test_pagination.py
test/test_query_column.py
test/test_sorting.py
test/test_sql_query.py
test/test_totals.py
test/test_transform.py
test/test_transform_result.py
webapi_active_query_builder/__init__.py
webapi_active_query_builder/api_client.py
webapi_active_query_builder/configuration.py
webapi_active_query_builder/rest.py
webapi_active_query_builder.egg-info/PKG-INFO
webapi_active_query_builder.egg-info/SOURCES.txt
webapi_active_query_builder.egg-info/dependency_links.txt
webapi_active_query_builder.egg-info/requires.txt
webapi_active_query_builder.egg-info/top_level.txt
webapi_active_query_builder/apis/__init__.py
webapi_active_query_builder/apis/active_query_builder_api.py
webapi_active_query_builder/models/__init__.py
webapi_active_query_builder/models/condition.py
webapi_active_query_builder/models/condition_group.py
webapi_active_query_builder/models/hidden_column.py
webapi_active_query_builder/models/pagination.py
webapi_active_query_builder/models/query_column.py
webapi_active_query_builder/models/sorting.py
webapi_active_query_builder/models/sql_query.py
webapi_active_query_builder/models/totals.py
webapi_active_query_builder/models/transform.py
webapi_active_query_builder/models/transform_result.py